wikes_toolkit/__init__.py
wikes_toolkit/toolkit.py
wikes_toolkit/base/evaluate.py
wikes_toolkit/base/graph_components.py
wikes_toolkit/base/versions.py
wikes_toolkit/esbm/esbm_eval.py
wikes_toolkit/esbm/esbm_graph.py
wikes_toolkit/esbm/esbm_graph_components.py
wikes_toolkit/esbm/esbm_nt_file_reader.py
wikes_toolkit/esbm/esbm_pandas_graph.py
wikes_toolkit/esbm/esbm_versions.py
wikes_toolkit/wikes/wikes_eval.py
wikes_toolkit/wikes/wikes_exporter.py
wikes_toolkit/wikes/wikes_graph.py
wikes_toolkit/wikes/wikes_pandas_graph.py
wikes_toolkit/wikes/wikes_versions.py
wikes_toolkit/wikes/wikies_graph_components.py
wikes_toolkit-1.0.22.dist-info/LICENSE
wikes_toolkit-1.0.22.dist-info/METADATA
wikes_toolkit-1.0.22.dist-info/WHEEL
wikes_toolkit-1.0.22.dist-info/top_level.txt
wikes_toolkit-1.0.22.dist-info/RECORD
