Metadata-Version: 2.1
Name: wikes_toolkit
Version: 1.0.22
Summary: Toolkit for Wiki-Entity-Summarization datasets (WikES) that helps end-users work with WikES datasets.
Author-email: Mo Sorkhpar <msorkhpar@outlook.com>
License: Attribution 4.0 International
Project-URL: Homepage, https://github.com/msorkhpar/wiki-entity-summarization-toolkit
Classifier: Development Status :: 5 - Production/Stable
Classifier: Intended Audience :: Developers
Classifier: License :: OSI Approved :: MIT License
Classifier: Programming Language :: Python :: 3
Classifier: Programming Language :: Python :: 3.10
Requires-Python: >=3.10
License-File: LICENSE
Requires-Dist: networkx<4.0,>=3.3
Requires-Dist: requests<3.0,>=2.26.0
Requires-Dist: tqdm<5.0,>=4.62.3
Requires-Dist: pandas<3.0,>=2.2.2
Requires-Dist: numpy<2.0,>=1.26.4
Requires-Dist: filehash<0.3,>=0.2.dev1
